ip_pj/timer/timer.v
//----------------------------
// タイマー モジュール
//----------------------------
module timer #(parameter WIDTH = 32)(
    input wire clk,
    input wire rst,
    input wire en,
    input wire oneshot,              // 1: ワンショット, 0: インターバル
    input wire [WIDTH-1:0] compare_val,
    output reg [WIDTH-1:0] count,
    output reg irq
);

always @(posedge clk or posedge rst) begin
    if (rst) begin
        count <= 0;
        irq <= 0;
    end else if (en) begin
        if (count + 1 >= compare_val) begin
            irq <= 1;
            if (oneshot)
                count <= count;       // ワンショット: カウント停止
            else
                count <= 0;           // インターバル: リスタート
        end else begin
            count <= count + 1;
            irq <= 0;
        end
    end else begin
        irq <= 0;
    end
end

endmodule


//----------------------------
// テストベンチ
//----------------------------
module timer_tb;

reg clk;
reg rst;
reg [4:0] en;
reg [4:0] oneshot;
wire [31:0] count0, count1, count2, count3;
wire [63:0] count4;
wire irq0, irq1, irq2, irq3, irq4;

// インスタンス生成

// 32bitタイマ4本
timer #(32) timer0 (.clk(clk), .rst(rst), .en(en[0]), .oneshot(oneshot[0]), .compare_val(32'd10), .count(count0), .irq(irq0));
timer #(32) timer1 (.clk(clk), .rst(rst), .en(en[1]), .oneshot(oneshot[1]), .compare_val(32'd20), .count(count1), .irq(irq1));
timer #(32) timer2 (.clk(clk), .rst(rst), .en(en[2]), .oneshot(oneshot[2]), .compare_val(32'd30), .count(count2), .irq(irq2));
timer #(32) timer3 (.clk(clk), .rst(rst), .en(en[3]), .oneshot(oneshot[3]), .compare_val(32'd40), .count(count3), .irq(irq3));

// 64bitタイマ1本
timer #(64) timer4 (.clk(clk), .rst(rst), .en(en[4]), .oneshot(oneshot[4]), .compare_val(64'd100), .count(count4), .irq(irq4));

// クロック生成
initial begin
    clk = 0;
    forever #5 clk = ~clk;
end

// テストシーケンス
initial begin
    $dumpfile("timer_tb.vcd");
    $dumpvars(0, timer_tb);

    rst = 1; en = 5'b00000; oneshot = 5'b00000;
    #20;
    rst = 0;

    en = 5'b11111;
    oneshot = 5'b01010;  // timer1とtimer3はワンショット、他はインターバル
    #500;

    en = 5'b00000;
    #50;

    $finish;
end

endmodule

ip_pj/timer/timer_tb.vcd
$date
	Fri Jul 04 22:26:01 2025
$end
$version
	Icarus Verilog
$end
$timescale
	1s
$end
$scope module timer_tb $end
$var wire 1 ! irq4 $end
$var wire 1 " irq3 $end
$var wire 1 # irq2 $end
$var wire 1 $ irq1 $end
$var wire 1 % irq0 $end
$var wire 64 & count4 [63:0] $end
$var wire 32 ' count3 [31:0] $end
$var wire 32 ( count2 [31:0] $end
$var wire 32 ) count1 [31:0] $end
$var wire 32 * count0 [31:0] $end
$var reg 1 + clk $end
$var reg 5 , en [4:0] $end
$var reg 5 - oneshot [4:0] $end
$var reg 1 . rst $end
$scope module timer0 $end
$var wire 1 + clk $end
$var wire 32 / compare_val [31:0] $end
$var wire 1 0 en $end
$var wire 1 1 oneshot $end
$var wire 1 . rst $end
$var parameter 32 2 WIDTH $end
$var reg 32 3 count [31:0] $end
$var reg 1 % irq $end
$upscope $end
$scope module timer1 $end
$var wire 1 + clk $end
$var wire 32 4 compare_val [31:0] $end
$var wire 1 5 en $end
$var wire 1 6 oneshot $end
$var wire 1 . rst $end
$var parameter 32 7 WIDTH $end
$var reg 32 8 count [31:0] $end
$var reg 1 $ irq $end
$upscope $end
$scope module timer2 $end
$var wire 1 + clk $end
$var wire 32 9 compare_val [31:0] $end
$var wire 1 : en $end
$var wire 1 ; oneshot $end
$var wire 1 . rst $end
$var parameter 32 < WIDTH $end
$var reg 32 = count [31:0] $end
$var reg 1 # irq $end
$upscope $end
$scope module timer3 $end
$var wire 1 + clk $end
$var wire 32 > compare_val [31:0] $end
$var wire 1 ? en $end
$var wire 1 @ oneshot $end
$var wire 1 . rst $end
$var parameter 32 A WIDTH $end
$var reg 32 B count [31:0] $end
$var reg 1 " irq $end
$upscope $end
$scope module timer4 $end
$var wire 1 + clk $end
$var wire 64 C compare_val [63:0] $end
$var wire 1 D en $end
$var wire 1 E oneshot $end
$var wire 1 . rst $end
$var parameter 32 F WIDTH $end
$var reg 64 G count [63:0] $end
$var reg 1 ! irq $end
$upscope $end
$upscope $end
$enddefinitions $end
$comment Show the parameter values. $end
$dumpall
b1000000 F
b100000 A
b100000 <
b100000 7
b100000 2
$end
#0
$dumpvars
b0 G
0E
0D
b1100100 C
b0 B
0@
0?
b101000 >
b0 =
0;
0:
b11110 9
b0 8
06
05
b10100 4
b0 3
01
00
b1010 /
1.
b0 -
b0 ,
0+
b0 *
b0 )
b0 (
b0 '
b0 &
0%
0$
0#
0"
0!
$end
#5
1+
#10
0+
#15
1+
#20
16
1@
10
15
1:
1?
1D
0+
b1010 -
b11111 ,
0.
#25
b1 &
b1 G
b1 '
b1 B
b1 (
b1 =
b1 )
b1 8
b1 *
b1 3
1+
#30
0+
#35
b10 *
b10 3
b10 )
b10 8
b10 (
b10 =
b10 '
b10 B
b10 &
b10 G
1+
#40
0+
#45
b11 &
b11 G
b11 '
b11 B
b11 (
b11 =
b11 )
b11 8
b11 *
b11 3
1+
#50
0+
#55
b100 *
b100 3
b100 )
b100 8
b100 (
b100 =
b100 '
b100 B
b100 &
b100 G
1+
#60
0+
#65
b101 &
b101 G
b101 '
b101 B
b101 (
b101 =
b101 )
b101 8
b101 *
b101 3
1+
#70
0+
#75
b110 *
b110 3
b110 )
b110 8
b110 (
b110 =
b110 '
b110 B
b110 &
b110 G
1+
#80
0+
#85
b111 &
b111 G
b111 '
b111 B
b111 (
b111 =
b111 )
b111 8
b111 *
b111 3
1+
#90
0+
#95
b1000 *
b1000 3
b1000 )
b1000 8
b1000 (
b1000 =
b1000 '
b1000 B
b1000 &
b1000 G
1+
#100
0+
#105
b1001 &
b1001 G
b1001 '
b1001 B
b1001 (
b1001 =
b1001 )
b1001 8
b1001 *
b1001 3
1+
#110
0+
#115
b0 *
b0 3
1%
b1010 )
b1010 8
b1010 (
b1010 =
b1010 '
b1010 B
b1010 &
b1010 G
1+
#120
0+
#125
b1011 &
b1011 G
b1011 '
b1011 B
b1011 (
b1011 =
b1011 )
b1011 8
0%
b1 *
b1 3
1+
#130
0+
#135
b10 *
b10 3
b1100 )
b1100 8
b1100 (
b1100 =
b1100 '
b1100 B
b1100 &
b1100 G
1+
#140
0+
#145
b1101 &
b1101 G
b1101 '
b1101 B
b1101 (
b1101 =
b1101 )
b1101 8
b11 *
b11 3
1+
#150
0+
#155
b100 *
b100 3
b1110 )
b1110 8
b1110 (
b1110 =
b1110 '
b1110 B
b1110 &
b1110 G
1+
#160
0+
#165
b1111 &
b1111 G
b1111 '
b1111 B
b1111 (
b1111 =
b1111 )
b1111 8
b101 *
b101 3
1+
#170
0+
#175
b110 *
b110 3
b10000 )
b10000 8
b10000 (
b10000 =
b10000 '
b10000 B
b10000 &
b10000 G
1+
#180
0+
#185
b10001 &
b10001 G
b10001 '
b10001 B
b10001 (
b10001 =
b10001 )
b10001 8
b111 *
b111 3
1+
#190
0+
#195
b1000 *
b1000 3
b10010 )
b10010 8
b10010 (
b10010 =
b10010 '
b10010 B
b10010 &
b10010 G
1+
#200
0+
#205
b10011 &
b10011 G
b10011 '
b10011 B
b10011 (
b10011 =
b10011 )
b10011 8
b1001 *
b1001 3
1+
#210
0+
#215
b0 *
b0 3
1%
1$
b10100 (
b10100 =
b10100 '
b10100 B
b10100 &
b10100 G
1+
#220
0+
#225
b10101 &
b10101 G
b10101 '
b10101 B
b10101 (
b10101 =
0%
b1 *
b1 3
1+
#230
0+
#235
b10 *
b10 3
b10110 (
b10110 =
b10110 '
b10110 B
b10110 &
b10110 G
1+
#240
0+
#245
b10111 &
b10111 G
b10111 '
b10111 B
b10111 (
b10111 =
b11 *
b11 3
1+
#250
0+
#255
b100 *
b100 3
b11000 (
b11000 =
b11000 '
b11000 B
b11000 &
b11000 G
1+
#260
0+
#265
b11001 &
b11001 G
b11001 '
b11001 B
b11001 (
b11001 =
b101 *
b101 3
1+
#270
0+
#275
b110 *
b110 3
b11010 (
b11010 =
b11010 '
b11010 B
b11010 &
b11010 G
1+
#280
0+
#285
b11011 &
b11011 G
b11011 '
b11011 B
b11011 (
b11011 =
b111 *
b111 3
1+
#290
0+
#295
b1000 *
b1000 3
b11100 (
b11100 =
b11100 '
b11100 B
b11100 &
b11100 G
1+
#300
0+
#305
b11101 &
b11101 G
b11101 '
b11101 B
b11101 (
b11101 =
b1001 *
b1001 3
1+
#310
0+
#315
b0 *
b0 3
1%
b0 (
b0 =
1#
b11110 '
b11110 B
b11110 &
b11110 G
1+
#320
0+
#325
b11111 &
b11111 G
b11111 '
b11111 B
0#
b1 (
b1 =
0%
b1 *
b1 3
1+
#330
0+
#335
b10 *
b10 3
b10 (
b10 =
b100000 '
b100000 B
b100000 &
b100000 G
1+
#340
0+
#345
b100001 &
b100001 G
b100001 '
b100001 B
b11 (
b11 =
b11 *
b11 3
1+
#350
0+
#355
b100 *
b100 3
b100 (
b100 =
b100010 '
b100010 B
b100010 &
b100010 G
1+
#360
0+
#365
b100011 &
b100011 G
b100011 '
b100011 B
b101 (
b101 =
b101 *
b101 3
1+
#370
0+
#375
b110 *
b110 3
b110 (
b110 =
b100100 '
b100100 B
b100100 &
b100100 G
1+
#380
0+
#385
b100101 &
b100101 G
b100101 '
b100101 B
b111 (
b111 =
b111 *
b111 3
1+
#390
0+
#395
b1000 *
b1000 3
b1000 (
b1000 =
b100110 '
b100110 B
b100110 &
b100110 G
1+
#400
0+
#405
b100111 &
b100111 G
b100111 '
b100111 B
b1001 (
b1001 =
b1001 *
b1001 3
1+
#410
0+
#415
b0 *
b0 3
1%
b1010 (
b1010 =
1"
b101000 &
b101000 G
1+
#420
0+
#425
b101001 &
b101001 G
b1011 (
b1011 =
0%
b1 *
b1 3
1+
#430
0+
#435
b10 *
b10 3
b1100 (
b1100 =
b101010 &
b101010 G
1+
#440
0+
#445
b101011 &
b101011 G
b1101 (
b1101 =
b11 *
b11 3
1+
#450
0+
#455
b100 *
b100 3
b1110 (
b1110 =
b101100 &
b101100 G
1+
#460
0+
#465
b101101 &
b101101 G
b1111 (
b1111 =
b101 *
b101 3
1+
#470
0+
#475
b110 *
b110 3
b10000 (
b10000 =
b101110 &
b101110 G
1+
#480
0+
#485
b101111 &
b101111 G
b10001 (
b10001 =
b111 *
b111 3
1+
#490
0+
#495
b1000 *
b1000 3
b10010 (
b10010 =
b110000 &
b110000 G
1+
#500
0+
#505
b110001 &
b110001 G
b10011 (
b10011 =
b1001 *
b1001 3
1+
#510
0+
#515
b0 *
b0 3
1%
b10100 (
b10100 =
b110010 &
b110010 G
1+
#520
00
05
0:
0?
0D
0+
b0 ,
#525
0"
0$
0%
1+
